autotz/__init__.py
autotz/main.py
autotz-1.0.0.dist-info/METADATA
autotz-1.0.0.dist-info/WHEEL
autotz-1.0.0.dist-info/entry_points.txt
autotz-1.0.0.dist-info/top_level.txt
autotz-1.0.0.dist-info/RECORD
