Metadata-Version: 2.2
Name: autotz
Version: 1.0.0
Summary: A simple tool to update the system timezone based on IP geolocation
Home-page: https://github.com/thorphar/autotz
Author: Harry Thorpe
Author-email: info@harrythorpe.co.uk
Classifier: Programming Language :: Python :: 3
Classifier: License :: OSI Approved :: MIT License
Classifier: Operating System :: POSIX :: Linux
Requires-Python: >=3.6
Requires-Dist: requests
Dynamic: author
Dynamic: author-email
Dynamic: classifier
Dynamic: description
Dynamic: description-content-type
Dynamic: home-page
Dynamic: requires-dist
Dynamic: requires-python
Dynamic: summary
